Lab 3B/fullSubtractor.v
module halfSubtractor(op1, op2, difference, borrow);
  
  input op1, op2;
  output difference, borrow;

  assign difference = op1 ^ op2; // XOR operation for difference
  assign borrow = ~op1 & op2; // AND operation for borrow

endmodule

module fullSubtractor(op1, op2, borrowIn, difference, borrowOut);
  
  input op1, op2, borrowIn;
  output difference, borrowOut;

  wire diff1, borrow1, borrow2;

  // First half subtractor
  halfSubtractor hs1(op1, op2, diff1, borrow1);

  // Second half subtractor
  halfSubtractor hs2(diff1, borrowIn, difference, borrow2);

  // Final borrow out calculation
  assign borrowOut = borrow1 | borrow2;

endmodule

Lab 3B/fullSubtractor_tb.v
`timescale 1ns / 1ps
`include "fullSubtractor.v"

module fullSubtractor_tb;

    // Inputs and outputs
    reg A, B, borrowIn;
    wire difference, borrowOut;

    // Instantiate the full subtractor module

    fullSubtractor uut(op1, op2, borrowIn, difference, borrowOut);

    initial begin

        $dumpfile("fullSubtractor_tb.vcd");
        $dumpvars(0, fullSubtractor_tb);

        // Test cases
        {A, B, borrowIn} = 3'd0; #20;
        {A, B, borrowIn} = 3'd1; #20;
        {A, B, borrowIn} = 3'd2; #20;
        {A, B, borrowIn} = 3'd3; #20;
        {A, B, borrowIn} = 3'd4; #20;
        {A, B, borrowIn} = 3'd5; #20;
        {A, B, borrowIn} = 3'd6; #20;
        {A, B, borrowIn} = 3'd7; #20;
        $display("Finished subtractions!");

    end

endmodule

Lab 3B/fullSubtractor_tb.vcd
$date
	Wed Apr 23 20:52:08 2025
$end
$version
	Icarus Verilog
$end
$timescale
	1ps
$end
$scope module fullSubtractor_tb $end
$var wire 1 ! op1 $end
$var wire 1 " op2 $end
$var wire 1 # difference $end
$var wire 1 $ borrowOut $end
$var reg 1 % A $end
$var reg 1 & B $end
$var reg 1 ' borrowIn $end
$scope module uut $end
$var wire 1 ' borrowIn $end
$var wire 1 $ borrowOut $end
$var wire 1 ! op1 $end
$var wire 1 " op2 $end
$var wire 1 # difference $end
$var wire 1 ( diff1 $end
$var wire 1 ) borrow2 $end
$var wire 1 * borrow1 $end
$scope module hs1 $end
$var wire 1 * borrow $end
$var wire 1 ( difference $end
$var wire 1 ! op1 $end
$var wire 1 " op2 $end
$upscope $end
$scope module hs2 $end
$var wire 1 ) borrow $end
$var wire 1 # difference $end
$var wire 1 ( op1 $end
$var wire 1 ' op2 $end
$upscope $end
$upscope $end
$upscope $end
$enddefinitions $end
$comment Show the parameter values. $end
$dumpall
$end
#0
$dumpvars
x*
0)
x(
0'
0&
0%
x$
x#
z"
z!
$end
#20000
x)
1'
#40000
0)
1&
0'
#60000
x)
1'
#80000
0)
1%
0&
0'
#100000
x)
1'
#120000
0)
1&
0'
#140000
x)
1'
